{
 "actions": [],
 "allow_rename": 1,
 "creation": "2024-12-10 16:14:42.829648",
 "doctype": "DocType",
 "editable_grid": 1,
 "engine": "InnoDB",
 "field_order": [
  "material_request"
 ],
 "fields": [
  {
   "fieldname": "material_request",
   "fieldtype": "Link",
   "label": "Material Request",
   "options": "Material Required"
  }
 ],
 "index_web_pages_for_search": 1,
 "istable": 1,
 "links": [],
 "modified": "2024-12-11 11:06:41.496132",
 "modified_by": "Administrator",
 "module": "Property Management Solution",
 "name": "Material",
 "owner": "Administrator",
 "permissions": [],
 "sort_field": "modified",
 "sort_order": "DESC",
 "states": []
}